merge_script.py
vcf_merger-2025.12.31.dist-info/licenses/LICENSE
vcf_merger-2025.12.31.dist-info/METADATA
vcf_merger-2025.12.31.dist-info/WHEEL
vcf_merger-2025.12.31.dist-info/entry_points.txt
vcf_merger-2025.12.31.dist-info/top_level.txt
vcf_merger-2025.12.31.dist-info/RECORD
