Metadata-Version: 2.4
Name: vcf-merger
Version: 2025.12.31
Summary: A utility to merge and deduplicate VCF contact files
Author-email: Faisal Ahmed Moshiur <faisalmoshiur+vcfmerger@gmail.com>
Maintainer-email: Faisal Ahmed Moshiur <faisalmoshiur+vcfmerger@gmail.com>
License: MIT
Project-URL: Homepage, https://github.com/fam007e/VCFmerger
Project-URL: Documentation, https://github.com/fam007e/VCFmerger/blob/main/README.md
Project-URL: Repository, https://github.com/fam007e/VCFmerger.git
Project-URL: Bug Tracker, https://github.com/fam007e/VCFmerger/issues
Project-URL: Changelog, https://github.com/fam007e/VCFmerger/blob/main/CHANGELOG.md
Keywords: vcf,vcard,contacts,merge,deduplicate,backup,phonebook,addressbook
Classifier: Development Status :: 5 - Production/Stable
Classifier: Intended Audience :: End Users/Desktop
Classifier: Intended Audience :: Developers
Classifier: Intended Audience :: System Administrators
Classifier: Topic :: Communications :: Email :: Address Book
Classifier: Topic :: Utilities
Classifier: Topic :: System :: Archiving :: Backup
Classifier: License :: OSI Approved :: MIT License
Classifier: Programming Language :: Python :: 3
Classifier: Programming Language :: Python :: 3.9
Classifier: Programming Language :: Python :: 3.10
Classifier: Programming Language :: Python :: 3.11
Classifier: Programming Language :: Python :: 3.12
Classifier: Programming Language :: Python :: 3.13
Classifier: Operating System :: OS Independent
Classifier: Operating System :: POSIX
Classifier: Operating System :: Microsoft :: Windows
Classifier: Operating System :: MacOS
Classifier: Environment :: Console
Requires-Python: >=3.9
License-File: LICENSE
Provides-Extra: dev
Requires-Dist: pylint>=2.0.0; extra == "dev"
Requires-Dist: black>=20.0.0; extra == "dev"
Requires-Dist: pytest>=6.0.0; extra == "dev"
Requires-Dist: pytest-cov>=2.0.0; extra == "dev"
Requires-Dist: mypy>=0.800; extra == "dev"
Requires-Dist: ruff>=0.1.0; extra == "dev"
Requires-Dist: build>=1.0.0; extra == "dev"
Provides-Extra: test
Requires-Dist: pytest>=6.0.0; extra == "test"
Requires-Dist: pytest-cov>=2.0.0; extra == "test"
Dynamic: license-file
